{
  "added": "2023-04-03T09:10:12.174Z",
  "info": {
    "description": "An API to generate charts and QR codes using QuickChart services.",
    "title": "QuickChart API",
    "version": "1.0.0",
    "x-apisguru-categories": [
      "developer_tools"
    ],
    "x-logo": {
      "url": "https://api.apis.guru/v2/cache/logo/https_quickchart.io_android-chrome-512x512.png"
    },
    "x-origin": [
      {
        "format": "openapi",
        "url": "https://quickchart.io/openapi.yaml",
        "version": "3.0"
      }
    ],
    "x-providerName": "quickchart.io"
  },
  "updated": "2023-04-03T09:10:12.174Z",
  "swaggerUrl": "https://api.apis.guru/v2/specs/quickchart.io/1.0.0/openapi.json",
  "swaggerYamlUrl": "https://api.apis.guru/v2/specs/quickchart.io/1.0.0/openapi.yaml",
  "openapiVer": "3.0.0",
  "link": "https://api.apis.guru/v2/specs/quickchart.io/1.0.0.json"
}