{
  "swagger": "2.0",
  "info": {
    "version": "1",
    "title": "vatapi.com",
    "x-providerName": "vatapi.com",
    "x-origin": {
      "format": "swagger",
      "version": "1.2",
      "url": "https://vatapi.com/api-docs.json"
    }
  },
  "paths": {
    "/country-code-check": {
      "get": {
        "tags": [
          "api"
        ],
        "operationId": "country_code_check",
        "summary": "Retrieve a countries VAT rates by its 2 digit country code",
        "parameters": [
          {
            "in": "header",
            "description": "Enter your API key",
            "name": "Apikey",
            "required": true,
            "type": "string"
          },
          {
            "in": "header",
            "description": "The default response type is application/json if you would like to receive an XML response then set this to XML",
            "name": "Response-Type",
            "type": "string"
          },
          {
            "in": "query",
            "description": "The 2 digit country code",
            "name": "code",
            "required": true,
            "type": "string"
          }
        ],
        "responses": {
          "200": {
            "description": "No response was specified",
            "schema": {
              "$ref": "#/definitions/Country_Code_Check"
            }
          }
        }
      }
    },
    "/currency-conversion": {
      "get": {
        "tags": [
          "api"
        ],
        "operationId": "currency_conversion",
        "summary": "Convert a currency",
        "parameters": [
          {
            "in": "header",
            "description": "Enter your API key",
            "name": "Apikey",
            "required": true,
            "type": "string"
          },
          {
            "in": "header",
            "description": "The default response type is application/json if you would like to receive an XML response then set this to XML",
            "name": "Response-Type",
            "type": "string"
          },
          {
            "in": "query",
            "description": "The currency code you are converting from",
            "name": "currency_from",
            "required": true,
            "type": "string"
          },
          {
            "in": "query",
            "description": "The currency code you are converting to",
            "name": "currency_to",
            "required": true,
            "type": "string"
          },
          {
            "in": "query",
            "description": "Optional, an amount you are wanting to convert. Leave blank to just get the current rate",
            "name": "amount",
            "required": false,
            "type": "integer"
          }
        ],
        "responses": {
          "200": {
            "description": "No response was specified",
            "schema": {
              "$ref": "#/definitions/Currency_Conversion"
            }
          }
        }
      }
    },
    "/invoice": {
      "post": {
        "tags": [
          "api"
        ],
        "operationId": "create_invoice",
        "summary": "Create a VAT invoice",
        "parameters": [
          {
            "in": "header",
            "description": "Enter your API key",
            "name": "Apikey",
            "required": true,
            "type": "string"
          },
          {
            "in": "header",
            "description": "The default response type is application/json if you would like to receive an XML response then set this to XML",
            "name": "Response-Type",
            "type": "string"
          },
          {
            "in": "body",
            "description": "Enter invoice data as JSON",
            "name": "body",
            "required": true,
            "schema": {
              "$ref": "#/definitions/Invoice_Data"
            }
          }
        ],
        "responses": {
          "200": {
            "description": "No response was specified",
            "schema": {
              "$ref": "#/definitions/Create_Invoice"
            }
          }
        }
      }
    },
    "/invoice/{id}": {
      "get": {
        "tags": [
          "api"
        ],
        "operationId": "get_invoice",
        "summary": "Retrieve an invoice",
        "parameters": [
          {
            "in": "header",
            "description": "Enter your API key",
            "name": "Apikey",
            "required": true,
            "type": "string"
          },
          {
            "in": "header",
            "description": "The default response type is application/json if you would like to receive an XML response then set this to XML",
            "name": "Response-Type",
            "type": "string"
          },
          {
            "in": "path",
            "description": "Enter the invoice id",
            "name": "id",
            "required": true,
            "type": "integer"
          }
        ],
        "responses": {
          "200": {
            "description": "No response was specified",
            "schema": {
              "$ref": "#/definitions/Retrieve_Invoice"
            }
          }
        }
      },
      "put": {
        "tags": [
          "api"
        ],
        "operationId": "invoice_update",
        "summary": "Update an existing invoice",
        "parameters": [
          {
            "in": "header",
            "description": "Enter your API key",
            "name": "Apikey",
            "required": true,
            "type": "string"
          },
          {
            "in": "header",
            "description": "The default response type is application/json if you would like to receive an XML response then set this to XML",
            "name": "Response-Type",
            "type": "string"
          },
          {
            "in": "path",
            "description": "Enter an invoice id",
            "name": "id",
            "required": true,
            "type": "integer"
          },
          {
            "in": "body",
            "description": "Enter invoice data as JSON",
            "name": "body",
            "required": true,
            "schema": {
              "$ref": "#/definitions/Update_Invoice_Array"
            }
          }
        ],
        "responses": {
          "200": {
            "description": "No response was specified",
            "schema": {
              "$ref": "#/definitions/Update_Invoice"
            }
          }
        }
      },
      "delete": {
        "tags": [
          "api"
        ],
        "operationId": "invoice_delete",
        "summary": "Delete an invoice",
        "parameters": [
          {
            "in": "header",
            "description": "Enter your API key",
            "name": "Apikey",
            "required": true,
            "type": "string"
          },
          {
            "in": "header",
            "description": "The default response type is application/json if you would like to receive an XML response then set this to XML",
            "name": "Response-Type",
            "type": "string"
          },
          {
            "in": "path",
            "description": "Enter an invoice id",
            "name": "id",
            "required": true,
            "type": "integer"
          }
        ],
        "responses": {
          "200": {
            "description": "No response was specified"
          }
        }
      }
    },
    "/ip-check": {
      "get": {
        "tags": [
          "api"
        ],
        "operationId": "ip_check",
        "summary": "Retrieve a countries VAT rates from an IP address",
        "parameters": [
          {
            "in": "header",
            "description": "Enter your API key",
            "name": "Apikey",
            "required": true,
            "type": "string"
          },
          {
            "in": "header",
            "description": "The default response type is application/json if you would like to receive an XML response then set this to XML",
            "name": "Response-Type",
            "type": "string"
          },
          {
            "in": "query",
            "description": "The IP address to search against",
            "name": "address",
            "required": true,
            "type": "string"
          }
        ],
        "responses": {
          "200": {
            "description": "No response was specified",
            "schema": {
              "$ref": "#/definitions/IP_Check"
            }
          }
        }
      }
    },
    "/vat-number-check": {
      "get": {
        "tags": [
          "api"
        ],
        "operationId": "vat_number_validate",
        "summary": "Validate a VAT number",
        "description": "<p>We highly recommend if you are able, to check a VAT number on your end first to save wasted API lookups. It maybe that your customer has simply entered the wrong format. <a href='http://www.braemoor.co.uk/software/vat.shtml' target='_blank'>Heres a client side way to check the format using Javascript</a></p>",
        "parameters": [
          {
            "in": "header",
            "description": "Enter your API key",
            "name": "Apikey",
            "required": true,
            "type": "string"
          },
          {
            "in": "header",
            "description": "The default response type is application/json if you would like to receive an XML response then set this to XML",
            "name": "Response-Type",
            "type": "string"
          },
          {
            "in": "query",
            "description": "The VAT number to validate",
            "name": "vatid",
            "required": true,
            "type": "string"
          }
        ],
        "responses": {
          "200": {
            "description": "No response was specified"
          }
        }
      }
    },
    "/vat-price": {
      "get": {
        "tags": [
          "api"
        ],
        "operationId": "convert_price",
        "summary": "Convert a price to or from VAT price.",
        "parameters": [
          {
            "in": "header",
            "description": "Enter your API key",
            "name": "Apikey",
            "required": true,
            "type": "string"
          },
          {
            "in": "header",
            "description": "The default response type is application/json if you would like to receive an XML response then set this to XML",
            "name": "Response-Type",
            "type": "string"
          },
          {
            "in": "query",
            "description": "The 2 digit country code",
            "name": "code",
            "required": true,
            "type": "string"
          },
          {
            "in": "query",
            "description": "The VAT rate to get the price for. Default: standard",
            "name": "country_rate",
            "required": false,
            "type": "string"
          },
          {
            "in": "query",
            "description": "The price you want converting",
            "name": "price",
            "required": true,
            "type": "integer"
          },
          {
            "in": "query",
            "description": "Optional, if the price is including VAT set the type to 'incl'. Otherwise the default is assumed as excluding VAT already, 'excl'",
            "name": "type",
            "required": false,
            "type": "string"
          }
        ],
        "responses": {
          "200": {
            "description": "No response was specified",
            "schema": {
              "$ref": "#/definitions/Convert_Price"
            }
          }
        }
      }
    },
    "/vat-rates": {
      "get": {
        "tags": [
          "api"
        ],
        "operationId": "vat_rates",
        "summary": "Retrieve all current EU VAT rates",
        "parameters": [
          {
            "in": "header",
            "description": "Enter your API key",
            "name": "Apikey",
            "required": true,
            "type": "string"
          },
          {
            "in": "header",
            "description": "The default response type is application/json if you would like to receive an XML response then set this to XML",
            "name": "Response-Type",
            "type": "string"
          }
        ],
        "responses": {
          "200": {
            "description": "No response was specified",
            "schema": {
              "$ref": "#/definitions/Vat_Rates"
            }
          }
        }
      }
    }
  },
  "host": "vatapi.com",
  "basePath": "/v1",
  "schemes": [
    "https"
  ],
  "tags": [
    {
      "name": "api",
      "description": "No description was specified"
    }
  ],
  "definitions": {
    "Country_Code_Check": {
      "required": [
        "country",
        "country_code",
        "rates",
        "status",
        "vat_applies"
      ],
      "properties": {
        "status": {
          "type": "integer",
          "description": "Response code"
        },
        "country_code": {
          "type": "string",
          "description": "The 2 digit country code"
        },
        "country": {
          "type": "string",
          "description": "The country name"
        },
        "vat_applies": {
          "type": "string",
          "description": "TRUE or FALSE, depending if country is within the EU."
        },
        "rates": {
          "$ref": "#/definitions/Country_Rates",
          "description": "An array of the EU VAT rates for that country"
        }
      }
    },
    "Country_Rates": {
      "required": [
        "parking",
        "reduced",
        "reduced_alt",
        "standard",
        "super_reduced"
      ],
      "properties": {
        "standard": {
          "$ref": "#/definitions/standard",
          "description": "The type of rate"
        },
        "reduced": {
          "$ref": "#/definitions/reduced",
          "description": "The type of rate"
        },
        "reduced_alt": {
          "$ref": "#/definitions/reduced_alt",
          "description": "The type of rate"
        },
        "super_reduced": {
          "$ref": "#/definitions/super_reduced",
          "description": "The type of rate"
        },
        "parking": {
          "$ref": "#/definitions/parking",
          "description": "The type of rate"
        }
      }
    },
    "standard": {
      "required": [
        "value"
      ],
      "properties": {
        "value": {
          "type": "integer",
          "description": "The % VAT rate"
        }
      }
    },
    "reduced": {
      "required": [
        "applies_to",
        "value"
      ],
      "properties": {
        "value": {
          "type": "integer",
          "description": "The % VAT rate"
        },
        "applies_to": {
          "type": "string",
          "description": "The type of goods the rate applies to"
        }
      }
    },
    "reduced_alt": {
      "required": [
        "applies_to",
        "value"
      ],
      "properties": {
        "value": {
          "type": "integer",
          "description": "The % VAT rate"
        },
        "applies_to": {
          "type": "string",
          "description": "The type of goods the rate applies to"
        }
      }
    },
    "super_reduced": {
      "required": [
        "applies_to",
        "value"
      ],
      "properties": {
        "value": {
          "type": "integer",
          "description": "The % VAT rate"
        },
        "applies_to": {
          "type": "string",
          "description": "The type of goods the rate applies to"
        }
      }
    },
    "parking": {
      "required": [
        "applies_to",
        "value"
      ],
      "properties": {
        "value": {
          "type": "integer",
          "description": "The % VAT rate"
        },
        "applies_to": {
          "type": "string",
          "description": "The type of goods the rate applies to"
        }
      }
    },
    "Vat_Rates": {
      "required": [
        "countries",
        "status"
      ],
      "properties": {
        "status": {
          "type": "integer",
          "description": "Response code"
        },
        "countries": {
          "type": "array",
          "items": {
            "$ref": "#/definitions/Vat_Rates_Countries"
          },
          "description": "An array of the EU VAT countries and their respective rates"
        }
      }
    },
    "Vat_Rates_Countries": {
      "required": [
        "country_code"
      ],
      "properties": {
        "country_code": {
          "$ref": "#/definitions/Country_Data",
          "description": "The 2 digit country code"
        }
      }
    },
    "Country_Data": {
      "required": [
        "country",
        "rates"
      ],
      "properties": {
        "country": {
          "type": "string",
          "description": "The country name"
        },
        "rates": {
          "$ref": "#/definitions/Country_Rates",
          "description": "An array of the rates for the country"
        }
      }
    },
    "IP_Check": {
      "required": [
        "country",
        "country_code",
        "rates",
        "status",
        "vat_applies"
      ],
      "properties": {
        "status": {
          "type": "integer",
          "description": "Response code"
        },
        "country_code": {
          "type": "string",
          "description": "The 2 digit country code"
        },
        "country": {
          "type": "string",
          "description": "The country name"
        },
        "vat_applies": {
          "type": "string",
          "description": "TRUE or FALSE, depending if country is within the EU."
        },
        "rates": {
          "$ref": "#/definitions/Country_Rates",
          "description": "An array of the EU VAT rates for that country"
        }
      }
    },
    "Convert_Price": {
      "required": [
        "country_code",
        "country_rate",
        "price_excl_vat",
        "price_incl_vat",
        "rate",
        "status",
        "vat"
      ],
      "properties": {
        "status": {
          "type": "integer",
          "description": "Response code"
        },
        "country_code": {
          "type": "string",
          "description": "The 2 digit country code"
        },
        "rate": {
          "type": "integer",
          "description": "The rate % for the country_rate"
        },
        "country_rate": {
          "type": "string",
          "description": "The country_rate"
        },
        "price_excl_vat": {
          "type": "integer",
          "description": "The price excluding VAT"
        },
        "price_incl_vat": {
          "type": "integer",
          "description": "The price including VAT"
        },
        "vat": {
          "type": "integer",
          "description": "The total amount of VAT applied"
        }
      }
    },
    "Currency_Conversion": {
      "required": [
        "currency_from",
        "currency_to",
        "rate",
        "status"
      ],
      "properties": {
        "status": {
          "type": "integer",
          "description": "Response code"
        },
        "currency_from": {
          "type": "string",
          "description": "The currency code you are converting from"
        },
        "currency_to": {
          "type": "integer",
          "description": "The currency code you are converting to"
        },
        "amount_from": {
          "type": "string",
          "description": "The amount you are converting from"
        },
        "amount_to": {
          "type": "string",
          "description": "The result amount you have converted to"
        },
        "rate": {
          "type": "string",
          "description": "The rate according to HMRC at time of sale"
        }
      }
    },
    "Create_Invoice": {
      "required": [
        "invoice",
        "status"
      ],
      "properties": {
        "status": {
          "type": "integer",
          "description": "Response code"
        },
        "invoice": {
          "$ref": "#/definitions/Invoice_Array",
          "description": "The new invoice object"
        }
      }
    },
    "Invoice_Data": {
      "required": [
        "business_address",
        "business_name",
        "currency_code",
        "items",
        "type",
        "vat_number"
      ],
      "properties": {
        "date": {
          "type": "string",
          "description": "The date the invoice was issued"
        },
        "tax_point": {
          "type": "string",
          "description": "(or 'time of supply') if this is different from the invoice date"
        },
        "type": {
          "type": "string",
          "description": "The type of invoice. Either 'sale' or 'refund'"
        },
        "currency_code": {
          "type": "string",
          "description": "3 character currency code for invoice"
        },
        "currency_code_conversion": {
          "type": "string",
          "description": "3 character currency code to be converted from original transaction currency"
        },
        "conversion_rate": {
          "type": "integer",
          "description": "The rate of conversion at time of supply"
        },
        "price_type": {
          "type": "string",
          "description": "Optional, if the price is including VAT set the type to 'incl'. Otherwise the default is assumed as excluding VAT already, 'excl'"
        },
        "business_address": {
          "type": "string",
          "description": "Your business address"
        },
        "customer_address": {
          "type": "string",
          "description": "Your customers address"
        },
        "business_name": {
          "type": "string",
          "description": "Your business name"
        },
        "customer_name": {
          "type": "string",
          "description": "Your customers name or trading name"
        },
        "vat_number": {
          "type": "string",
          "description": "Your VAT number"
        },
        "customer_vat_number": {
          "type": "string",
          "description": "Optional customers VAT number"
        },
        "zero_rated": {
          "type": "string",
          "description": "To Zero-Rate the VAT, set to true."
        },
        "discount_rate": {
          "type": "string",
          "description": "The discount rate per item"
        },
        "notes": {
          "type": "string",
          "description": "Add a note to the invoice."
        },
        "items": {
          "type": "array",
          "items": {
            "$ref": "#/definitions/Invoice_Items"
          },
          "description": "An array of your invoice items"
        }
      }
    },
    "Invoice_Array": {
      "required": [
        "business_address",
        "business_name",
        "currency_code",
        "date",
        "discount_total",
        "invoice_number",
        "invoice_url",
        "items",
        "subtotal",
        "tax_point",
        "total",
        "type",
        "vat_number",
        "vat_total"
      ],
      "properties": {
        "invoice_number": {
          "type": "integer",
          "description": "A sequential invoice number"
        },
        "date": {
          "type": "string",
          "description": "The date the invoice was issued"
        },
        "tax_point": {
          "type": "string",
          "description": "(or 'time of supply') if this is different from the invoice date"
        },
        "type": {
          "type": "string",
          "description": "The type of invoice. Either 'sale' or 'refund'"
        },
        "currency_code": {
          "type": "string",
          "description": "3 character currency code for invoice"
        },
        "currency_code_conversion": {
          "type": "string",
          "description": "3 character currency code to be converted from original transaction currency"
        },
        "conversion_rate": {
          "type": "integer",
          "description": "The rate of conversion at time of supply"
        },
        "business_name": {
          "type": "string",
          "description": "Your business name"
        },
        "business_address": {
          "type": "string",
          "description": "Your business address"
        },
        "customer_name": {
          "type": "string",
          "description": "Your customers name or trading name"
        },
        "customer_address": {
          "type": "string",
          "description": "Your customers address"
        },
        "vat_number": {
          "type": "string",
          "description": "Your VAT number"
        },
        "customer_vat_number": {
          "type": "string",
          "description": "Customers VAT number"
        },
        "subtotal": {
          "type": "integer",
          "description": "Total amount excluding VAT"
        },
        "vat_total": {
          "type": "integer",
          "description": "Total amount of VAT"
        },
        "discount_rate": {
          "type": "integer",
          "description": "The discount rate per item"
        },
        "discount_total": {
          "type": "integer",
          "description": "Total amount of discount"
        },
        "total": {
          "type": "integer",
          "description": "Total amount of including VAT"
        },
        "logo_url": {
          "type": "string",
          "description": "A URL to your logo image. Must be SSL hosted. https://sslimagehost.com is recommended"
        },
        "invoice_url": {
          "type": "string",
          "description": "A perminant URL to your VAT invoice"
        },
        "notes": {
          "type": "string",
          "description": "Any notes attached to the invoice"
        },
        "items": {
          "type": "array",
          "items": {
            "$ref": "#/definitions/Invoice_Items"
          },
          "description": "An array of your invoice items"
        }
      }
    },
    "Invoice_Items": {
      "required": [
        "description",
        "price_each",
        "quantity",
        "vat_rate"
      ],
      "properties": {
        "description": {
          "type": "string",
          "description": "The item line description"
        },
        "quantity": {
          "type": "integer",
          "description": "The quantity of the item"
        },
        "price_each": {
          "type": "integer",
          "description": "The price of the individual item (Ex VAT)"
        },
        "vat_rate": {
          "type": "integer",
          "description": "The VAT rate at which the item is charged"
        }
      }
    },
    "Retrieve_Invoice": {
      "required": [
        "invoice",
        "status"
      ],
      "properties": {
        "status": {
          "type": "string",
          "description": "Response code"
        },
        "invoice": {
          "$ref": "#/definitions/Retrieve_Invoice_Array",
          "description": "The invoice array"
        }
      }
    },
    "Update_Invoice": {
      "required": [
        "invoice",
        "status"
      ],
      "properties": {
        "status": {
          "type": "string",
          "description": "Response code"
        },
        "invoice": {
          "$ref": "#/definitions/Retrieve_Invoice_Array",
          "description": "The invoice array"
        }
      }
    },
    "Update_Invoice_Array": {
      "required": [
        "business_address",
        "business_name",
        "currency_code",
        "customervat_number",
        "items",
        "type"
      ],
      "properties": {
        "date": {
          "type": "string",
          "description": "The date the invoice was issued"
        },
        "tax_point": {
          "type": "string",
          "description": "(or 'time of supply') if this is different from the invoice date"
        },
        "type": {
          "type": "string",
          "description": "The type of invoice. Either 'sale' or 'refund'"
        },
        "currency_code": {
          "type": "string",
          "description": "3 character currency code for invoice"
        },
        "currency_code_conversion": {
          "type": "string",
          "description": "3 character currency code to be converted from original transaction currency"
        },
        "conversion_rate": {
          "type": "integer",
          "description": "The rate of conversion at time of supply"
        },
        "business_address": {
          "type": "string",
          "description": "Your business address"
        },
        "customer_address": {
          "type": "string",
          "description": "Your customers address"
        },
        "business_name": {
          "type": "string",
          "description": "Your business name"
        },
        "customer_name": {
          "type": "string",
          "description": "Your customers name or trading name"
        },
        "vat_number": {
          "type": "string",
          "description": "Your VAT number"
        },
        "customervat_number": {
          "type": "string",
          "description": "Customers VAT number"
        },
        "discount_rate": {
          "type": "string",
          "description": "The discount rate per item"
        },
        "logo_url": {
          "type": "string",
          "description": "A URL to your logo image. Must be SSL hosted. https://sslimagehost.com is recommended"
        },
        "notes": {
          "type": "string",
          "description": "Add a note to the invoice."
        },
        "items": {
          "type": "array",
          "items": {
            "$ref": "#/definitions/Invoice_Items"
          },
          "description": "An array of your invoice items"
        }
      }
    },
    "Retrieve_Invoice_Array": {
      "required": [
        "business_address",
        "business_name",
        "currency_code",
        "date",
        "discount_total",
        "id",
        "invoice_url",
        "items",
        "subtotal",
        "tax_point",
        "total",
        "type",
        "vat_number",
        "vat_total"
      ],
      "properties": {
        "id": {
          "type": "integer",
          "description": "The invoice ID"
        },
        "date": {
          "type": "string",
          "description": "The date the invoice was issued"
        },
        "tax_point": {
          "type": "string",
          "description": "(or 'time of supply') if this is different from the invoice date"
        },
        "type": {
          "type": "string",
          "description": "The type of invoice. Either 'sale' or 'refund'"
        },
        "currency_code": {
          "type": "string",
          "description": "3 character currency code for invoice"
        },
        "currency_code_conversion": {
          "type": "string",
          "description": "3 character currency code to be converted from original transaction currency"
        },
        "conversion_rate": {
          "type": "integer",
          "description": "The rate of conversion at time of supply"
        },
        "price_type": {
          "type": "string",
          "description": "Optional, if the price is including VAT set the type to 'incl'. Otherwise the default is assumed as excluding VAT already, 'excl'"
        },
        "business_name": {
          "type": "string",
          "description": "Your business name"
        },
        "business_address": {
          "type": "string",
          "description": "Your business address"
        },
        "customer_name": {
          "type": "string",
          "description": "Your customers name or trading name"
        },
        "customer_address": {
          "type": "string",
          "description": "Your customers address"
        },
        "vat_number": {
          "type": "string",
          "description": "Your VAT number"
        },
        "customer_vat_number": {
          "type": "string",
          "description": "Optional, customers VAT number"
        },
        "zero_rated": {
          "type": "string",
          "description": "To Zero-Rate the VAT, set to true."
        },
        "subtotal": {
          "type": "integer",
          "description": "Total amount excluding VAT"
        },
        "vat_total": {
          "type": "integer",
          "description": "Total amount of VAT"
        },
        "discount_rate": {
          "type": "integer",
          "description": "The discount rate per item"
        },
        "discount_total": {
          "type": "integer",
          "description": "Total amount of discount"
        },
        "total": {
          "type": "integer",
          "description": "Total amount of including VAT"
        },
        "logo_url": {
          "type": "string",
          "description": "A URL to your logo image. Must be SSL hosted. https://sslimagehost.com is recommended"
        },
        "invoice_url": {
          "type": "string",
          "description": "A perminant URL to your VAT invoice"
        },
        "notes": {
          "type": "string",
          "description": "Any notes attached to the invoice"
        },
        "items": {
          "type": "array",
          "items": {
            "$ref": "#/definitions/Invoice_Items"
          },
          "description": "An array of your invoice items"
        }
      }
    }
  }
}